{
  "app": {
    "[project]/frontend/src/app/(auth)/forgot-password/page": [
      "static/media/83afe278b6a6bb3c-s.p.3a6ba036.woff2"
    ],
    "[project]/frontend/src/app/(auth)/login/page": [
      "static/media/83afe278b6a6bb3c-s.p.3a6ba036.woff2"
    ],
    "[project]/frontend/src/app/(auth)/phone/page": [
      "static/media/83afe278b6a6bb3c-s.p.3a6ba036.woff2"
    ],
    "[project]/frontend/src/app/(auth)/register/page": [
      "static/media/83afe278b6a6bb3c-s.p.3a6ba036.woff2"
    ],
    "[project]/frontend/src/app/(projects)/projects/dashboard/page": [
      "static/media/83afe278b6a6bb3c-s.p.3a6ba036.woff2"
    ],
    "[project]/frontend/src/app/(projects)/projects/page": [
      "static/media/83afe278b6a6bb3c-s.p.3a6ba036.woff2"
    ],
    "[project]/frontend/src/app/(projects)/projects/settings/page": [
      "static/media/83afe278b6a6bb3c-s.p.3a6ba036.woff2"
    ],
    "[project]/frontend/src/app/(projects)/projects/team/page": [
      "static/media/83afe278b6a6bb3c-s.p.3a6ba036.woff2"
    ],
    "[project]/frontend/src/app/(projects)/projects/views/page": [
      "static/media/83afe278b6a6bb3c-s.p.3a6ba036.woff2"
    ],
    "[project]/frontend/src/app/(public)/test-dynamic-demo/page": [
      "static/media/83afe278b6a6bb3c-s.p.3a6ba036.woff2"
    ],
    "[project]/frontend/src/app/(website)/[slug]/page": [
      "static/media/83afe278b6a6bb3c-s.p.3a6ba036.woff2"
    ],
    "[project]/frontend/src/app/(website)/bai-viet/[slug]/page": [
      "static/media/83afe278b6a6bb3c-s.p.3a6ba036.woff2"
    ],
    "[project]/frontend/src/app/(website)/bai-viet/page": [
      "static/media/83afe278b6a6bb3c-s.p.3a6ba036.woff2"
    ],
    "[project]/frontend/src/app/(website)/gio-hang/page": [
      "static/media/83afe278b6a6bb3c-s.p.3a6ba036.woff2"
    ],
    "[project]/frontend/src/app/(website)/page": [
      "static/media/83afe278b6a6bb3c-s.p.3a6ba036.woff2"
    ],
    "[project]/frontend/src/app/(website)/san-pham/[slug]/page": [
      "static/media/83afe278b6a6bb3c-s.p.3a6ba036.woff2"
    ],
    "[project]/frontend/src/app/(website)/san-pham/page": [
      "static/media/83afe278b6a6bb3c-s.p.3a6ba036.woff2"
    ],
    "[project]/frontend/src/app/(website)/thanh-toan/page": [
      "static/media/83afe278b6a6bb3c-s.p.3a6ba036.woff2"
    ],
    "[project]/frontend/src/app/_not-found/page": [
      "static/media/83afe278b6a6bb3c-s.p.3a6ba036.woff2"
    ],
    "[project]/frontend/src/app/admin/affiliate/browse/page": [
      "static/media/83afe278b6a6bb3c-s.p.3a6ba036.woff2"
    ],
    "[project]/frontend/src/app/admin/affiliate/campaigns/[id]/applications/page": [
      "static/media/83afe278b6a6bb3c-s.p.3a6ba036.woff2"
    ],
    "[project]/frontend/src/app/admin/affiliate/campaigns/page": [
      "static/media/83afe278b6a6bb3c-s.p.3a6ba036.woff2"
    ],
    "[project]/frontend/src/app/admin/affiliate/dashboard/page": [
      "static/media/83afe278b6a6bb3c-s.p.3a6ba036.woff2"
    ],
    "[project]/frontend/src/app/admin/affiliate/links/page": [
      "static/media/83afe278b6a6bb3c-s.p.3a6ba036.woff2"
    ],
    "[project]/frontend/src/app/admin/affiliate/page": [
      "static/media/83afe278b6a6bb3c-s.p.3a6ba036.woff2"
    ],
    "[project]/frontend/src/app/admin/affiliate/payments/page": [
      "static/media/83afe278b6a6bb3c-s.p.3a6ba036.woff2"
    ],
    "[project]/frontend/src/app/admin/callcenter/page": [
      "static/media/83afe278b6a6bb3c-s.p.3a6ba036.woff2"
    ],
    "[project]/frontend/src/app/admin/categories/page": [
      "static/media/83afe278b6a6bb3c-s.p.3a6ba036.woff2"
    ],
    "[project]/frontend/src/app/admin/dashboard/page": [
      "static/media/83afe278b6a6bb3c-s.p.3a6ba036.woff2"
    ],
    "[project]/frontend/src/app/admin/data-management/page": [
      "static/media/83afe278b6a6bb3c-s.p.3a6ba036.woff2"
    ],
    "[project]/frontend/src/app/admin/dynamic-demo/page": [
      "static/media/83afe278b6a6bb3c-s.p.3a6ba036.woff2"
    ],
    "[project]/frontend/src/app/admin/filemanager/page": [
      "static/media/83afe278b6a6bb3c-s.p.3a6ba036.woff2"
    ],
    "[project]/frontend/src/app/admin/hr/employee/[id]/documents/page": [
      "static/media/83afe278b6a6bb3c-s.p.3a6ba036.woff2"
    ],
    "[project]/frontend/src/app/admin/hr/employee/[id]/edit/page": [
      "static/media/83afe278b6a6bb3c-s.p.3a6ba036.woff2"
    ],
    "[project]/frontend/src/app/admin/hr/employee/[id]/page": [
      "static/media/83afe278b6a6bb3c-s.p.3a6ba036.woff2"
    ],
    "[project]/frontend/src/app/admin/hr/employee/new/page": [
      "static/media/83afe278b6a6bb3c-s.p.3a6ba036.woff2"
    ],
    "[project]/frontend/src/app/admin/hr/employees/page": [
      "static/media/83afe278b6a6bb3c-s.p.3a6ba036.woff2"
    ],
    "[project]/frontend/src/app/admin/hr/offboarding/[id]/page": [
      "static/media/83afe278b6a6bb3c-s.p.3a6ba036.woff2"
    ],
    "[project]/frontend/src/app/admin/hr/offboarding/new/page": [
      "static/media/83afe278b6a6bb3c-s.p.3a6ba036.woff2"
    ],
    "[project]/frontend/src/app/admin/hr/offboarding/page": [
      "static/media/83afe278b6a6bb3c-s.p.3a6ba036.woff2"
    ],
    "[project]/frontend/src/app/admin/hr/onboarding/[id]/page": [
      "static/media/83afe278b6a6bb3c-s.p.3a6ba036.woff2"
    ],
    "[project]/frontend/src/app/admin/hr/onboarding/new/page": [
      "static/media/83afe278b6a6bb3c-s.p.3a6ba036.woff2"
    ],
    "[project]/frontend/src/app/admin/hr/onboarding/page": [
      "static/media/83afe278b6a6bb3c-s.p.3a6ba036.woff2"
    ],
    "[project]/frontend/src/app/admin/hr/page": [
      "static/media/83afe278b6a6bb3c-s.p.3a6ba036.woff2"
    ],
    "[project]/frontend/src/app/admin/hr/reports/page": [
      "static/media/83afe278b6a6bb3c-s.p.3a6ba036.woff2"
    ],
    "[project]/frontend/src/app/admin/menu/page": [
      "static/media/83afe278b6a6bb3c-s.p.3a6ba036.woff2"
    ],
    "[project]/frontend/src/app/admin/orders/page": [
      "static/media/83afe278b6a6bb3c-s.p.3a6ba036.woff2"
    ],
    "[project]/frontend/src/app/admin/page": [
      "static/media/83afe278b6a6bb3c-s.p.3a6ba036.woff2"
    ],
    "[project]/frontend/src/app/admin/pagebuilder/page": [
      "static/media/83afe278b6a6bb3c-s.p.3a6ba036.woff2"
    ],
    "[project]/frontend/src/app/admin/products/[id]/page": [
      "static/media/83afe278b6a6bb3c-s.p.3a6ba036.woff2"
    ],
    "[project]/frontend/src/app/admin/products/create/page": [
      "static/media/83afe278b6a6bb3c-s.p.3a6ba036.woff2"
    ],
    "[project]/frontend/src/app/admin/products/page": [
      "static/media/83afe278b6a6bb3c-s.p.3a6ba036.woff2"
    ],
    "[project]/frontend/src/app/admin/projects/page": [
      "static/media/83afe278b6a6bb3c-s.p.3a6ba036.woff2"
    ],
    "[project]/frontend/src/app/admin/request-access/page": [
      "static/media/83afe278b6a6bb3c-s.p.3a6ba036.woff2"
    ],
    "[project]/frontend/src/app/admin/settings/website/page": [
      "static/media/83afe278b6a6bb3c-s.p.3a6ba036.woff2"
    ],
    "[project]/frontend/src/app/admin/support-chat/ai-settings/page": [
      "static/media/83afe278b6a6bb3c-s.p.3a6ba036.woff2"
    ],
    "[project]/frontend/src/app/admin/support-chat/page": [
      "static/media/83afe278b6a6bb3c-s.p.3a6ba036.woff2"
    ],
    "[project]/frontend/src/app/admin/tasks/[id]/page": [
      "static/media/83afe278b6a6bb3c-s.p.3a6ba036.woff2"
    ],
    "[project]/frontend/src/app/admin/tasks/page": [
      "static/media/83afe278b6a6bb3c-s.p.3a6ba036.woff2"
    ],
    "[project]/frontend/src/app/admin/users/page": [
      "static/media/83afe278b6a6bb3c-s.p.3a6ba036.woff2"
    ],
    "[project]/frontend/src/app/affiliate-access/page": [
      "static/media/83afe278b6a6bb3c-s.p.3a6ba036.woff2"
    ],
    "[project]/frontend/src/app/demo/advanced-table-demo/page": [
      "static/media/83afe278b6a6bb3c-s.p.3a6ba036.woff2"
    ],
    "[project]/frontend/src/app/demo/ai/page": [
      "static/media/83afe278b6a6bb3c-s.p.3a6ba036.woff2"
    ],
    "[project]/frontend/src/app/demo/carousel/page": [
      "static/media/83afe278b6a6bb3c-s.p.3a6ba036.woff2"
    ],
    "[project]/frontend/src/app/demo/chatbot/page": [
      "static/media/83afe278b6a6bb3c-s.p.3a6ba036.woff2"
    ],
    "[project]/frontend/src/app/demo/login/page": [
      "static/media/83afe278b6a6bb3c-s.p.3a6ba036.woff2"
    ],
    "[project]/frontend/src/app/demo/monitoring/page": [
      "static/media/83afe278b6a6bb3c-s.p.3a6ba036.woff2"
    ],
    "[project]/frontend/src/app/demo/page": [
      "static/media/83afe278b6a6bb3c-s.p.3a6ba036.woff2"
    ],
    "[project]/frontend/src/app/demo/pwa/page": [
      "static/media/83afe278b6a6bb3c-s.p.3a6ba036.woff2"
    ],
    "[project]/frontend/src/app/demo/toast/page": [
      "static/media/83afe278b6a6bb3c-s.p.3a6ba036.woff2"
    ],
    "[project]/frontend/src/app/ketoan/detailhoadon/page": [
      "static/media/83afe278b6a6bb3c-s.p.3a6ba036.woff2"
    ],
    "[project]/frontend/src/app/ketoan/listhoadon/page": [
      "static/media/83afe278b6a6bb3c-s.p.3a6ba036.woff2"
    ],
    "[project]/frontend/src/app/ketoan/page": [
      "static/media/83afe278b6a6bb3c-s.p.3a6ba036.woff2"
    ],
    "[project]/frontend/src/app/ketoan/sanpham/page": [
      "static/media/83afe278b6a6bb3c-s.p.3a6ba036.woff2"
    ],
    "[project]/frontend/src/app/ketoan/xuatnhapton/page": [
      "static/media/83afe278b6a6bb3c-s.p.3a6ba036.woff2"
    ],
    "[project]/frontend/src/app/lms/admin/categories/page": [
      "static/media/83afe278b6a6bb3c-s.p.3a6ba036.woff2"
    ],
    "[project]/frontend/src/app/lms/admin/courses/[id]/edit/page": [
      "static/media/83afe278b6a6bb3c-s.p.3a6ba036.woff2"
    ],
    "[project]/frontend/src/app/lms/admin/courses/[id]/page": [
      "static/media/83afe278b6a6bb3c-s.p.3a6ba036.woff2"
    ],
    "[project]/frontend/src/app/lms/admin/courses/create-with-ai/page": [
      "static/media/83afe278b6a6bb3c-s.p.3a6ba036.woff2"
    ],
    "[project]/frontend/src/app/lms/admin/courses/create/page": [
      "static/media/83afe278b6a6bb3c-s.p.3a6ba036.woff2"
    ],
    "[project]/frontend/src/app/lms/admin/courses/page": [
      "static/media/83afe278b6a6bb3c-s.p.3a6ba036.woff2"
    ],
    "[project]/frontend/src/app/lms/admin/enrollments/page": [
      "static/media/83afe278b6a6bb3c-s.p.3a6ba036.woff2"
    ],
    "[project]/frontend/src/app/lms/admin/instructors/page": [
      "static/media/83afe278b6a6bb3c-s.p.3a6ba036.woff2"
    ],
    "[project]/frontend/src/app/lms/admin/page": [
      "static/media/83afe278b6a6bb3c-s.p.3a6ba036.woff2"
    ],
    "[project]/frontend/src/app/lms/admin/quizzes/page": [
      "static/media/83afe278b6a6bb3c-s.p.3a6ba036.woff2"
    ],
    "[project]/frontend/src/app/lms/admin/reports/page": [
      "static/media/83afe278b6a6bb3c-s.p.3a6ba036.woff2"
    ],
    "[project]/frontend/src/app/lms/admin/settings/page": [
      "static/media/83afe278b6a6bb3c-s.p.3a6ba036.woff2"
    ],
    "[project]/frontend/src/app/lms/admin/students/[id]/page": [
      "static/media/83afe278b6a6bb3c-s.p.3a6ba036.woff2"
    ],
    "[project]/frontend/src/app/lms/admin/students/page": [
      "static/media/83afe278b6a6bb3c-s.p.3a6ba036.woff2"
    ],
    "[project]/frontend/src/app/lms/certificates/verify/page": [
      "static/media/83afe278b6a6bb3c-s.p.3a6ba036.woff2"
    ],
    "[project]/frontend/src/app/lms/courses/[slug]/page": [
      "static/media/83afe278b6a6bb3c-s.p.3a6ba036.woff2"
    ],
    "[project]/frontend/src/app/lms/courses/page": [
      "static/media/83afe278b6a6bb3c-s.p.3a6ba036.woff2"
    ],
    "[project]/frontend/src/app/lms/instructor/courses/[id]/edit/page": [
      "static/media/83afe278b6a6bb3c-s.p.3a6ba036.woff2"
    ],
    "[project]/frontend/src/app/lms/instructor/courses/[id]/lessons/page": [
      "static/media/83afe278b6a6bb3c-s.p.3a6ba036.woff2"
    ],
    "[project]/frontend/src/app/lms/instructor/courses/[id]/manage/page": [
      "static/media/83afe278b6a6bb3c-s.p.3a6ba036.woff2"
    ],
    "[project]/frontend/src/app/lms/instructor/courses/[id]/quizzes/page": [
      "static/media/83afe278b6a6bb3c-s.p.3a6ba036.woff2"
    ],
    "[project]/frontend/src/app/lms/instructor/courses/create/page": [
      "static/media/83afe278b6a6bb3c-s.p.3a6ba036.woff2"
    ],
    "[project]/frontend/src/app/lms/instructor/dashboard/page": [
      "static/media/83afe278b6a6bb3c-s.p.3a6ba036.woff2"
    ],
    "[project]/frontend/src/app/lms/learn/[slug]/page": [
      "static/media/83afe278b6a6bb3c-s.p.3a6ba036.woff2"
    ],
    "[project]/frontend/src/app/lms/my-certificates/page": [
      "static/media/83afe278b6a6bb3c-s.p.3a6ba036.woff2"
    ],
    "[project]/frontend/src/app/lms/my-learning/page": [
      "static/media/83afe278b6a6bb3c-s.p.3a6ba036.woff2"
    ],
    "[project]/frontend/src/app/lms/page": [
      "static/media/83afe278b6a6bb3c-s.p.3a6ba036.woff2"
    ],
    "[project]/frontend/src/app/lms/student/page": [
      "static/media/83afe278b6a6bb3c-s.p.3a6ba036.woff2"
    ],
    "[project]/frontend/src/app/maintenance/page": [
      "static/media/83afe278b6a6bb3c-s.p.3a6ba036.woff2"
    ]
  },
  "appUsingSizeAdjust": true,
  "pages": {},
  "pagesUsingSizeAdjust": false
}